livedc/__init__.py
livedc/desc.py
livedc/calendar/JetLag_datecount.py
livedc/calendar/__init__.py
livedc/calendar/cntdate.py
livedc/format/__init__.py
livedc/format/html2pdf.py
livedc/health/__init__.py
livedc/health/workout.py
livedc/math/__init__.py
livedc/math/financial/__init__.py
livedc/math/financial/compound.py
livedc/math/game/__init__.py
livedc/math/game/nash.py
livedc/math/or/__init__.py
livedc/math/or/diet2.py
livedc/math/or/example.py
livedc/math/or/lp.py
livedc/vr/tdm23.vr
livedc/vr/tdm23.vr.pkl
livedc-0.0.17.dist-info/licenses/LICENSE
livedc-0.0.17.dist-info/METADATA
livedc-0.0.17.dist-info/WHEEL
livedc-0.0.17.dist-info/entry_points.txt
livedc-0.0.17.dist-info/top_level.txt
livedc-0.0.17.dist-info/RECORD
