Metadata-Version: 2.4
Name: livedc
Version: 0.0.17
Summary: Useful mathmatical models/caculators for daily life and cloud deployment
Author-email: jinsanity <jinsanityff@gmail.com>
License: MIT License
Project-URL: Homepage, https://github.com/jinsanity07git/livedc
Keywords: cpu,gpu,benchmark
Classifier: License :: OSI Approved :: MIT License
Classifier: Programming Language :: Python
Classifier: Programming Language :: Python :: 3
Requires-Python: >=3.6
License-File: LICENSE
Requires-Dist: nodespecs>=0.0.15
Provides-Extra: dev
Requires-Dist: GPUtil; extra == "dev"
Requires-Dist: pip-tools; extra == "dev"
Requires-Dist: psutil>=5.9.5; extra == "dev"
Requires-Dist: toml; extra == "dev"
Requires-Dist: pyomo==6.2; extra == "dev"
Dynamic: license-file
